[{"id":32327066,"node_id":"MDEwOlJlcG9zaXRvcnkzMjMyNzA2Ng==","name":"docker-dd-agent","full_name":"goekhanm/docker-dd-agent","private":false,"owner":{"login":"goekhanm","id":8457420,"node_id":"MDQ6VXNlcjg0NTc0MjA=","avatar_url":"https://avatars.githubusercontent.com/u/8457420?v=4","gravatar_id":"","url":"https://api.github.com/users/goekhanm","html_url":"https://github.com/goekhanm","followers_url":"https://api.github.com/users/goekhanm/followers","following_url":"https://api.github.com/users/goekhanm/following{/other_user}","gists_url":"https://api.github.com/users/goekhanm/gists{/gist_id}","starred_url":"https://api.github.com/users/goekhanm/starred{/owner}{/repo}","subscriptions_url":"https://api.github.com/users/goekhanm/subscriptions","organizations_url":"https://api.github.com/users/goekhanm/orgs","repos_url":"https://api.github.com/users/goekhanm/repos","events_url":"https://api.github.com/users/goekhanm/events{/privacy}","received_events_url":"https://api.github.com/users/goekhanm/received_events","type":"User","site_admin":false},"html_url":"https://github.com/goekhanm/docker-dd-agent","description":"Datadog Agent Dockerfile for Trusted Builds.","fork":true,"url":"https://api.github.com/repos/goekhanm/docker-dd-agent","forks_url":"https://api.github.com/repos/goekhanm/docker-dd-agent/forks","keys_url":"https://api.github.com/repos/goekhanm/docker-dd-agent/keys{/key_id}","collaborators_url":"https://api.github.com/repos/goekhanm/docker-dd-agent/collaborators{/collaborator}","teams_url":"https://api.github.com/repos/goekhanm/docker-dd-agent/teams","hooks_url":"https://api.github.com/repos/goekhanm/docker-dd-agent/hooks","issue_events_url":"https://api.github.com/repos/goekhanm/docker-dd-agent/issues/events{/number}","events_url":"https://api.github.com/repos/goekhanm/docker-dd-agent/events","assignees_url":"https://api.github.com/repos/goekhanm/docker-dd-agent/assignees{/user}","branches_url":"https://api.github.com/repos/goekhanm/docker-dd-agent/branches{/branch}","tags_url":"https://api.github.com/repos/goekhanm/docker-dd-agent/tags","blobs_url":"https://api.github.com/repos/goekhanm/docker-dd-agent/git/blobs{/sha}","git_tags_url":"https://api.github.com/repos/goekhanm/docker-dd-agent/git/tags{/sha}","git_refs_url":"https://api.github.com/repos/goekhanm/docker-dd-agent/git/refs{/sha}","trees_url":"https://api.github.com/repos/goekhanm/docker-dd-agent/git/trees{/sha}","statuses_url":"https://api.github.com/repos/goekhanm/docker-dd-agent/statuses/{sha}","languages_url":"https://api.github.com/repos/goekhanm/docker-dd-agent/languages","stargazers_url":"https://api.github.com/repos/goekhanm/docker-dd-agent/stargazers","contributors_url":"https://api.github.com/repos/goekhanm/docker-dd-agent/contributors","subscribers_url":"https://api.github.com/repos/goekhanm/docker-dd-agent/subscribers","subscription_url":"https://api.github.com/repos/goekhanm/docker-dd-agent/subscription","commits_url":"https://api.github.com/repos/goekhanm/docker-dd-agent/commits{/sha}","git_commits_url":"https://api.github.com/repos/goekhanm/docker-dd-agent/git/commits{/sha}","comments_url":"https://api.github.com/repos/goekhanm/docker-dd-agent/comments{/number}","issue_comment_url":"https://api.github.com/repos/goekhanm/docker-dd-agent/issues/comments{/number}","contents_url":"https://api.github.com/repos/goekhanm/docker-dd-agent/contents/{+path}","compare_url":"https://api.github.com/repos/goekhanm/docker-dd-agent/compare/{base}...{head}","merges_url":"https://api.github.com/repos/goekhanm/docker-dd-agent/merges","archive_url":"https://api.github.com/repos/goekhanm/docker-dd-agent/{archive_format}{/ref}","downloads_url":"https://api.github.com/repos/goekhanm/docker-dd-agent/downloads","issues_url":"https://api.github.com/repos/goekhanm/docker-dd-agent/issues{/number}","pulls_url":"https://api.github.com/repos/goekhanm/docker-dd-agent/pulls{/number}","milestones_url":"https://api.github.com/repos/goekhanm/docker-dd-agent/milestones{/number}","notifications_url":"https://api.github.com/repos/goekhanm/docker-dd-agent/notifications{?since,all,participating}","labels_url":"https://api.github.com/repos/goekhanm/docker-dd-agent/labels{/name}","releases_url":"https://api.github.com/repos/goekhanm/docker-dd-agent/releases{/id}","deployments_url":"https://api.github.com/repos/goekhanm/docker-dd-agent/deployments","created_at":"2015-03-16T13:34:35Z","updated_at":"2015-03-18T15:58:21Z","pushed_at":"2015-03-18T15:58:20Z","git_url":"git://github.com/goekhanm/docker-dd-agent.git","ssh_url":"git@github.com:goekhanm/docker-dd-agent.git","clone_url":"https://github.com/goekhanm/docker-dd-agent.git","svn_url":"https://github.com/goekhanm/docker-dd-agent","homepage":"https://index.docker.io/u/datadog/docker-dd-agent/","size":152,"stargazers_count":0,"watchers_count":0,"language":"Shell","has_issues":false,"has_projects":true,"has_downloads":true,"has_wiki":true,"has_pages":false,"has_discussions":false,"forks_count":0,"mirror_url":null,"archived":false,"disabled":false,"open_issues_count":0,"license":null,"allow_forking":true,"is_template":false,"web_commit_signoff_required":false,"topics":[],"visibility":"public","forks":0,"open_issues":0,"watchers":0,"default_branch":"master","permissions":{"admin":false,"maintain":false,"push":false,"triage":false,"pull":true}},{"id":212070088,"node_id":"MDEwOlJlcG9zaXRvcnkyMTIwNzAwODg=","name":"docker-workshop","full_name":"goekhanm/docker-workshop","private":false,"owner":{"login":"goekhanm","id":8457420,"node_id":"MDQ6VXNlcjg0NTc0MjA=","avatar_url":"https://avatars.githubusercontent.com/u/8457420?v=4","gravatar_id":"","url":"https://api.github.com/users/goekhanm","html_url":"https://github.com/goekhanm","followers_url":"https://api.github.com/users/goekhanm/followers","following_url":"https://api.github.com/users/goekhanm/following{/other_user}","gists_url":"https://api.github.com/users/goekhanm/gists{/gist_id}","starred_url":"https://api.github.com/users/goekhanm/starred{/owner}{/repo}","subscriptions_url":"https://api.github.com/users/goekhanm/subscriptions","organizations_url":"https://api.github.com/users/goekhanm/orgs","repos_url":"https://api.github.com/users/goekhanm/repos","events_url":"https://api.github.com/users/goekhanm/events{/privacy}","received_events_url":"https://api.github.com/users/goekhanm/received_events","type":"User","site_admin":false},"html_url":"https://github.com/goekhanm/docker-workshop","description":null,"fork":true,"url":"https://api.github.com/repos/goekhanm/docker-workshop","forks_url":"https://api.github.com/repos/goekhanm/docker-workshop/forks","keys_url":"https://api.github.com/repos/goekhanm/docker-workshop/keys{/key_id}","collaborators_url":"https://api.github.com/repos/goekhanm/docker-workshop/collaborators{/collaborator}","teams_url":"https://api.github.com/repos/goekhanm/docker-workshop/teams","hooks_url":"https://api.github.com/repos/goekhanm/docker-workshop/hooks","issue_events_url":"https://api.github.com/repos/goekhanm/docker-workshop/issues/events{/number}","events_url":"https://api.github.com/repos/goekhanm/docker-workshop/events","assignees_url":"https://api.github.com/repos/goekhanm/docker-workshop/assignees{/user}","branches_url":"https://api.github.com/repos/goekhanm/docker-workshop/branches{/branch}","tags_url":"https://api.github.com/repos/goekhanm/docker-workshop/tags","blobs_url":"https://api.github.com/repos/goekhanm/docker-workshop/git/blobs{/sha}","git_tags_url":"https://api.github.com/repos/goekhanm/docker-workshop/git/tags{/sha}","git_refs_url":"https://api.github.com/repos/goekhanm/docker-workshop/git/refs{/sha}","trees_url":"https://api.github.com/repos/goekhanm/docker-workshop/git/trees{/sha}","statuses_url":"https://api.github.com/repos/goekhanm/docker-workshop/statuses/{sha}","languages_url":"https://api.github.com/repos/goekhanm/docker-workshop/languages","stargazers_url":"https://api.github.com/repos/goekhanm/docker-workshop/stargazers","contributors_url":"https://api.github.com/repos/goekhanm/docker-workshop/contributors","subscribers_url":"https://api.github.com/repos/goekhanm/docker-workshop/subscribers","subscription_url":"https://api.github.com/repos/goekhanm/docker-workshop/subscription","commits_url":"https://api.github.com/repos/goekhanm/docker-workshop/commits{/sha}","git_commits_url":"https://api.github.com/repos/goekhanm/docker-workshop/git/commits{/sha}","comments_url":"https://api.github.com/repos/goekhanm/docker-workshop/comments{/number}","issue_comment_url":"https://api.github.com/repos/goekhanm/docker-workshop/issues/comments{/number}","contents_url":"https://api.github.com/repos/goekhanm/docker-workshop/contents/{+path}","compare_url":"https://api.github.com/repos/goekhanm/docker-workshop/compare/{base}...{head}","merges_url":"https://api.github.com/repos/goekhanm/docker-workshop/merges","archive_url":"https://api.github.com/repos/goekhanm/docker-workshop/{archive_format}{/ref}","downloads_url":"https://api.github.com/repos/goekhanm/docker-workshop/downloads","issues_url":"https://api.github.com/repos/goekhanm/docker-workshop/issues{/number}","pulls_url":"https://api.github.com/repos/goekhanm/docker-workshop/pulls{/number}","milestones_url":"https://api.github.com/repos/goekhanm/docker-workshop/milestones{/number}","notifications_url":"https://api.github.com/repos/goekhanm/docker-workshop/notifications{?since,all,participating}","labels_url":"https://api.github.com/repos/goekhanm/docker-workshop/labels{/name}","releases_url":"https://api.github.com/repos/goekhanm/docker-workshop/releases{/id}","deployments_url":"https://api.github.com/repos/goekhanm/docker-workshop/deployments","created_at":"2019-10-01T10:37:39Z","updated_at":"2019-10-01T10:37:40Z","pushed_at":"2019-10-01T11:20:13Z","git_url":"git://github.com/goekhanm/docker-workshop.git","ssh_url":"git@github.com:goekhanm/docker-workshop.git","clone_url":"https://github.com/goekhanm/docker-workshop.git","svn_url":"https://github.com/goekhanm/docker-workshop","homepage":null,"size":14217,"stargazers_count":0,"watchers_count":0,"language":null,"has_issues":false,"has_projects":true,"has_downloads":true,"has_wiki":true,"has_pages":false,"has_discussions":false,"forks_count":0,"mirror_url":null,"archived":false,"disabled":false,"open_issues_count":0,"license":null,"allow_forking":true,"is_template":false,"web_commit_signoff_required":false,"topics":[],"visibility":"public","forks":0,"open_issues":0,"watchers":0,"default_branch":"master","permissions":{"admin":false,"maintain":false,"push":false,"triage":false,"pull":true}},{"id":121401193,"node_id":"MDEwOlJlcG9zaXRvcnkxMjE0MDExOTM=","name":"openshift-ansible-contrib","full_name":"goekhanm/openshift-ansible-contrib","private":false,"owner":{"login":"goekhanm","id":8457420,"node_id":"MDQ6VXNlcjg0NTc0MjA=","avatar_url":"https://avatars.githubusercontent.com/u/8457420?v=4","gravatar_id":"","url":"https://api.github.com/users/goekhanm","html_url":"https://github.com/goekhanm","followers_url":"https://api.github.com/users/goekhanm/followers","following_url":"https://api.github.com/users/goekhanm/following{/other_user}","gists_url":"https://api.github.com/users/goekhanm/gists{/gist_id}","starred_url":"https://api.github.com/users/goekhanm/starred{/owner}{/repo}","subscriptions_url":"https://api.github.com/users/goekhanm/subscriptions","organizations_url":"https://api.github.com/users/goekhanm/orgs","repos_url":"https://api.github.com/users/goekhanm/repos","events_url":"https://api.github.com/users/goekhanm/events{/privacy}","received_events_url":"https://api.github.com/users/goekhanm/received_events","type":"User","site_admin":false},"html_url":"https://github.com/goekhanm/openshift-ansible-contrib","description":"Additional roles and playbooks for OpenShift installation and management","fork":true,"url":"https://api.github.com/repos/goekhanm/openshift-ansible-contrib","forks_url":"https://api.github.com/repos/goekhanm/openshift-ansible-contrib/forks","keys_url":"https://api.github.com/repos/goekhanm/openshift-ansible-contrib/keys{/key_id}","collaborators_url":"https://api.github.com/repos/goekhanm/openshift-ansible-contrib/collaborators{/collaborator}","teams_url":"https://api.github.com/repos/goekhanm/openshift-ansible-contrib/teams","hooks_url":"https://api.github.com/repos/goekhanm/openshift-ansible-contrib/hooks","issue_events_url":"https://api.github.com/repos/goekhanm/openshift-ansible-contrib/issues/events{/number}","events_url":"https://api.github.com/repos/goekhanm/openshift-ansible-contrib/events","assignees_url":"https://api.github.com/repos/goekhanm/openshift-ansible-contrib/assignees{/user}","branches_url":"https://api.github.com/repos/goekhanm/openshift-ansible-contrib/branches{/branch}","tags_url":"https://api.github.com/repos/goekhanm/openshift-ansible-contrib/tags","blobs_url":"https://api.github.com/repos/goekhanm/openshift-ansible-contrib/git/blobs{/sha}","git_tags_url":"https://api.github.com/repos/goekhanm/openshift-ansible-contrib/git/tags{/sha}","git_refs_url":"https://api.github.com/repos/goekhanm/openshift-ansible-contrib/git/refs{/sha}","trees_url":"https://api.github.com/repos/goekhanm/openshift-ansible-contrib/git/trees{/sha}","statuses_url":"https://api.github.com/repos/goekhanm/openshift-ansible-contrib/statuses/{sha}","languages_url":"https://api.github.com/repos/goekhanm/openshift-ansible-contrib/languages","stargazers_url":"https://api.github.com/repos/goekhanm/openshift-ansible-contrib/stargazers","contributors_url":"https://api.github.com/repos/goekhanm/openshift-ansible-contrib/contributors","subscribers_url":"https://api.github.com/repos/goekhanm/openshift-ansible-contrib/subscribers","subscription_url":"https://api.github.com/repos/goekhanm/openshift-ansible-contrib/subscription","commits_url":"https://api.github.com/repos/goekhanm/openshift-ansible-contrib/commits{/sha}","git_commits_url":"https://api.github.com/repos/goekhanm/openshift-ansible-contrib/git/commits{/sha}","comments_url":"https://api.github.com/repos/goekhanm/openshift-ansible-contrib/comments{/number}","issue_comment_url":"https://api.github.com/repos/goekhanm/openshift-ansible-contrib/issues/comments{/number}","contents_url":"https://api.github.com/repos/goekhanm/openshift-ansible-contrib/contents/{+path}","compare_url":"https://api.github.com/repos/goekhanm/openshift-ansible-contrib/compare/{base}...{head}","merges_url":"https://api.github.com/repos/goekhanm/openshift-ansible-contrib/merges","archive_url":"https://api.github.com/repos/goekhanm/openshift-ansible-contrib/{archive_format}{/ref}","downloads_url":"https://api.github.com/repos/goekhanm/openshift-ansible-contrib/downloads","issues_url":"https://api.github.com/repos/goekhanm/openshift-ansible-contrib/issues{/number}","pulls_url":"https://api.github.com/repos/goekhanm/openshift-ansible-contrib/pulls{/number}","milestones_url":"https://api.github.com/repos/goekhanm/openshift-ansible-contrib/milestones{/number}","notifications_url":"https://api.github.com/repos/goekhanm/openshift-ansible-contrib/notifications{?since,all,participating}","labels_url":"https://api.github.com/repos/goekhanm/openshift-ansible-contrib/labels{/name}","releases_url":"https://api.github.com/repos/goekhanm/openshift-ansible-contrib/releases{/id}","deployments_url":"https://api.github.com/repos/goekhanm/openshift-ansible-contrib/deployments","created_at":"2018-02-13T15:44:37Z","updated_at":"2019-04-06T19:42:25Z","pushed_at":"2018-02-13T16:01:20Z","git_url":"git://github.com/goekhanm/openshift-ansible-contrib.git","ssh_url":"git@github.com:goekhanm/openshift-ansible-contrib.git","clone_url":"https://github.com/goekhanm/openshift-ansible-contrib.git","svn_url":"https://github.com/goekhanm/openshift-ansible-contrib","homepage":"https://www.openshift.com","size":5683,"stargazers_count":0,"watchers_count":0,"language":"Python","has_issues":false,"has_projects":true,"has_downloads":true,"has_wiki":false,"has_pages":false,"has_discussions":false,"forks_count":0,"mirror_url":null,"archived":false,"disabled":false,"open_issues_count":0,"license":{"key":"apache-2.0","name":"Apache License 2.0","spdx_id":"Apache-2.0","url":"https://api.github.com/licenses/apache-2.0","node_id":"MDc6TGljZW5zZTI="},"allow_forking":true,"is_template":false,"web_commit_signoff_required":false,"topics":[],"visibility":"public","forks":0,"open_issues":0,"watchers":0,"default_branch":"master","permissions":{"admin":false,"maintain":false,"push":false,"triage":false,"pull":true}},{"id":117105421,"node_id":"MDEwOlJlcG9zaXRvcnkxMTcxMDU0MjE=","name":"simple-java-maven-app","full_name":"goekhanm/simple-java-maven-app","private":false,"owner":{"login":"goekhanm","id":8457420,"node_id":"MDQ6VXNlcjg0NTc0MjA=","avatar_url":"https://avatars.githubusercontent.com/u/8457420?v=4","gravatar_id":"","url":"https://api.github.com/users/goekhanm","html_url":"https://github.com/goekhanm","followers_url":"https://api.github.com/users/goekhanm/followers","following_url":"https://api.github.com/users/goekhanm/following{/other_user}","gists_url":"https://api.github.com/users/goekhanm/gists{/gist_id}","starred_url":"https://api.github.com/users/goekhanm/starred{/owner}{/repo}","subscriptions_url":"https://api.github.com/users/goekhanm/subscriptions","organizations_url":"https://api.github.com/users/goekhanm/orgs","repos_url":"https://api.github.com/users/goekhanm/repos","events_url":"https://api.github.com/users/goekhanm/events{/privacy}","received_events_url":"https://api.github.com/users/goekhanm/received_events","type":"User","site_admin":false},"html_url":"https://github.com/goekhanm/simple-java-maven-app","description":"For an introductory tutorial on how to use Jenkins to build a simple Java application with Maven.","fork":true,"url":"https://api.github.com/repos/goekhanm/simple-java-maven-app","forks_url":"https://api.github.com/repos/goekhanm/simple-java-maven-app/forks","keys_url":"https://api.github.com/repos/goekhanm/simple-java-maven-app/keys{/key_id}","collaborators_url":"https://api.github.com/repos/goekhanm/simple-java-maven-app/collaborators{/collaborator}","teams_url":"https://api.github.com/repos/goekhanm/simple-java-maven-app/teams","hooks_url":"https://api.github.com/repos/goekhanm/simple-java-maven-app/hooks","issue_events_url":"https://api.github.com/repos/goekhanm/simple-java-maven-app/issues/events{/number}","events_url":"https://api.github.com/repos/goekhanm/simple-java-maven-app/events","assignees_url":"https://api.github.com/repos/goekhanm/simple-java-maven-app/assignees{/user}","branches_url":"https://api.github.com/repos/goekhanm/simple-java-maven-app/branches{/branch}","tags_url":"https://api.github.com/repos/goekhanm/simple-java-maven-app/tags","blobs_url":"https://api.github.com/repos/goekhanm/simple-java-maven-app/git/blobs{/sha}","git_tags_url":"https://api.github.com/repos/goekhanm/simple-java-maven-app/git/tags{/sha}","git_refs_url":"https://api.github.com/repos/goekhanm/simple-java-maven-app/git/refs{/sha}","trees_url":"https://api.github.com/repos/goekhanm/simple-java-maven-app/git/trees{/sha}","statuses_url":"https://api.github.com/repos/goekhanm/simple-java-maven-app/statuses/{sha}","languages_url":"https://api.github.com/repos/goekhanm/simple-java-maven-app/languages","stargazers_url":"https://api.github.com/repos/goekhanm/simple-java-maven-app/stargazers","contributors_url":"https://api.github.com/repos/goekhanm/simple-java-maven-app/contributors","subscribers_url":"https://api.github.com/repos/goekhanm/simple-java-maven-app/subscribers","subscription_url":"https://api.github.com/repos/goekhanm/simple-java-maven-app/subscription","commits_url":"https://api.github.com/repos/goekhanm/simple-java-maven-app/commits{/sha}","git_commits_url":"https://api.github.com/repos/goekhanm/simple-java-maven-app/git/commits{/sha}","comments_url":"https://api.github.com/repos/goekhanm/simple-java-maven-app/comments{/number}","issue_comment_url":"https://api.github.com/repos/goekhanm/simple-java-maven-app/issues/comments{/number}","contents_url":"https://api.github.com/repos/goekhanm/simple-java-maven-app/contents/{+path}","compare_url":"https://api.github.com/repos/goekhanm/simple-java-maven-app/compare/{base}...{head}","merges_url":"https://api.github.com/repos/goekhanm/simple-java-maven-app/merges","archive_url":"https://api.github.com/repos/goekhanm/simple-java-maven-app/{archive_format}{/ref}","downloads_url":"https://api.github.com/repos/goekhanm/simple-java-maven-app/downloads","issues_url":"https://api.github.com/repos/goekhanm/simple-java-maven-app/issues{/number}","pulls_url":"https://api.github.com/repos/goekhanm/simple-java-maven-app/pulls{/number}","milestones_url":"https://api.github.com/repos/goekhanm/simple-java-maven-app/milestones{/number}","notifications_url":"https://api.github.com/repos/goekhanm/simple-java-maven-app/notifications{?since,all,participating}","labels_url":"https://api.github.com/repos/goekhanm/simple-java-maven-app/labels{/name}","releases_url":"https://api.github.com/repos/goekhanm/simple-java-maven-app/releases{/id}","deployments_url":"https://api.github.com/repos/goekhanm/simple-java-maven-app/deployments","created_at":"2018-01-11T13:40:36Z","updated_at":"2018-01-11T13:40:37Z","pushed_at":"2017-12-19T03:45:32Z","git_url":"git://github.com/goekhanm/simple-java-maven-app.git","ssh_url":"git@github.com:goekhanm/simple-java-maven-app.git","clone_url":"https://github.com/goekhanm/simple-java-maven-app.git","svn_url":"https://github.com/goekhanm/simple-java-maven-app","homepage":"","size":13,"stargazers_count":0,"watchers_count":0,"language":"Java","has_issues":false,"has_projects":true,"has_downloads":true,"has_wiki":true,"has_pages":false,"has_discussions":false,"forks_count":0,"mirror_url":null,"archived":false,"disabled":false,"open_issues_count":0,"license":null,"allow_forking":true,"is_template":false,"web_commit_signoff_required":false,"topics":[],"visibility":"public","forks":0,"open_issues":0,"watchers":0,"default_branch":"master","permissions":{"admin":false,"maintain":false,"push":false,"triage":false,"pull":true}},{"id":109847657,"node_id":"MDEwOlJlcG9zaXRvcnkxMDk4NDc2NTc=","name":"spring-mvc-showcase","full_name":"goekhanm/spring-mvc-showcase","private":false,"owner":{"login":"goekhanm","id":8457420,"node_id":"MDQ6VXNlcjg0NTc0MjA=","avatar_url":"https://avatars.githubusercontent.com/u/8457420?v=4","gravatar_id":"","url":"https://api.github.com/users/goekhanm","html_url":"https://github.com/goekhanm","followers_url":"https://api.github.com/users/goekhanm/followers","following_url":"https://api.github.com/users/goekhanm/following{/other_user}","gists_url":"https://api.github.com/users/goekhanm/gists{/gist_id}","starred_url":"https://api.github.com/users/goekhanm/starred{/owner}{/repo}","subscriptions_url":"https://api.github.com/users/goekhanm/subscriptions","organizations_url":"https://api.github.com/users/goekhanm/orgs","repos_url":"https://api.github.com/users/goekhanm/repos","events_url":"https://api.github.com/users/goekhanm/events{/privacy}","received_events_url":"https://api.github.com/users/goekhanm/received_events","type":"User","site_admin":false},"html_url":"https://github.com/goekhanm/spring-mvc-showcase","description":"Demonstrates the features of the Spring MVC web framework","fork":true,"url":"https://api.github.com/repos/goekhanm/spring-mvc-showcase","forks_url":"https://api.github.com/repos/goekhanm/spring-mvc-showcase/forks","keys_url":"https://api.github.com/repos/goekhanm/spring-mvc-showcase/keys{/key_id}","collaborators_url":"https://api.github.com/repos/goekhanm/spring-mvc-showcase/collaborators{/collaborator}","teams_url":"https://api.github.com/repos/goekhanm/spring-mvc-showcase/teams","hooks_url":"https://api.github.com/repos/goekhanm/spring-mvc-showcase/hooks","issue_events_url":"https://api.github.com/repos/goekhanm/spring-mvc-showcase/issues/events{/number}","events_url":"https://api.github.com/repos/goekhanm/spring-mvc-showcase/events","assignees_url":"https://api.github.com/repos/goekhanm/spring-mvc-showcase/assignees{/user}","branches_url":"https://api.github.com/repos/goekhanm/spring-mvc-showcase/branches{/branch}","tags_url":"https://api.github.com/repos/goekhanm/spring-mvc-showcase/tags","blobs_url":"https://api.github.com/repos/goekhanm/spring-mvc-showcase/git/blobs{/sha}","git_tags_url":"https://api.github.com/repos/goekhanm/spring-mvc-showcase/git/tags{/sha}","git_refs_url":"https://api.github.com/repos/goekhanm/spring-mvc-showcase/git/refs{/sha}","trees_url":"https://api.github.com/repos/goekhanm/spring-mvc-showcase/git/trees{/sha}","statuses_url":"https://api.github.com/repos/goekhanm/spring-mvc-showcase/statuses/{sha}","languages_url":"https://api.github.com/repos/goekhanm/spring-mvc-showcase/languages","stargazers_url":"https://api.github.com/repos/goekhanm/spring-mvc-showcase/stargazers","contributors_url":"https://api.github.com/repos/goekhanm/spring-mvc-showcase/contributors","subscribers_url":"https://api.github.com/repos/goekhanm/spring-mvc-showcase/subscribers","subscription_url":"https://api.github.com/repos/goekhanm/spring-mvc-showcase/subscription","commits_url":"https://api.github.com/repos/goekhanm/spring-mvc-showcase/commits{/sha}","git_commits_url":"https://api.github.com/repos/goekhanm/spring-mvc-showcase/git/commits{/sha}","comments_url":"https://api.github.com/repos/goekhanm/spring-mvc-showcase/comments{/number}","issue_comment_url":"https://api.github.com/repos/goekhanm/spring-mvc-showcase/issues/comments{/number}","contents_url":"https://api.github.com/repos/goekhanm/spring-mvc-showcase/contents/{+path}","compare_url":"https://api.github.com/repos/goekhanm/spring-mvc-showcase/compare/{base}...{head}","merges_url":"https://api.github.com/repos/goekhanm/spring-mvc-showcase/merges","archive_url":"https://api.github.com/repos/goekhanm/spring-mvc-showcase/{archive_format}{/ref}","downloads_url":"https://api.github.com/repos/goekhanm/spring-mvc-showcase/downloads","issues_url":"https://api.github.com/repos/goekhanm/spring-mvc-showcase/issues{/number}","pulls_url":"https://api.github.com/repos/goekhanm/spring-mvc-showcase/pulls{/number}","milestones_url":"https://api.github.com/repos/goekhanm/spring-mvc-showcase/milestones{/number}","notifications_url":"https://api.github.com/repos/goekhanm/spring-mvc-showcase/notifications{?since,all,participating}","labels_url":"https://api.github.com/repos/goekhanm/spring-mvc-showcase/labels{/name}","releases_url":"https://api.github.com/repos/goekhanm/spring-mvc-showcase/releases{/id}","deployments_url":"https://api.github.com/repos/goekhanm/spring-mvc-showcase/deployments","created_at":"2017-11-07T14:39:09Z","updated_at":"2017-11-07T14:39:10Z","pushed_at":"2017-11-07T15:07:42Z","git_url":"git://github.com/goekhanm/spring-mvc-showcase.git","ssh_url":"git@github.com:goekhanm/spring-mvc-showcase.git","clone_url":"https://github.com/goekhanm/spring-mvc-showcase.git","svn_url":"https://github.com/goekhanm/spring-mvc-showcase","homepage":"","size":649,"stargazers_count":0,"watchers_count":0,"language":"Java","has_issues":false,"has_projects":true,"has_downloads":true,"has_wiki":true,"has_pages":false,"has_discussions":false,"forks_count":0,"mirror_url":null,"archived":false,"disabled":false,"open_issues_count":0,"license":null,"allow_forking":true,"is_template":false,"web_commit_signoff_required":false,"topics":[],"visibility":"public","forks":0,"open_issues":0,"watchers":0,"default_branch":"master","permissions":{"admin":false,"maintain":false,"push":false,"triage":false,"pull":true}},{"id":109855972,"node_id":"MDEwOlJlcG9zaXRvcnkxMDk4NTU5NzI=","name":"wordpress","full_name":"goekhanm/wordpress","private":false,"owner":{"login":"goekhanm","id":8457420,"node_id":"MDQ6VXNlcjg0NTc0MjA=","avatar_url":"https://avatars.githubusercontent.com/u/8457420?v=4","gravatar_id":"","url":"https://api.github.com/users/goekhanm","html_url":"https://github.com/goekhanm","followers_url":"https://api.github.com/users/goekhanm/followers","following_url":"https://api.github.com/users/goekhanm/following{/other_user}","gists_url":"https://api.github.com/users/goekhanm/gists{/gist_id}","starred_url":"https://api.github.com/users/goekhanm/starred{/owner}{/repo}","subscriptions_url":"https://api.github.com/users/goekhanm/subscriptions","organizations_url":"https://api.github.com/users/goekhanm/orgs","repos_url":"https://api.github.com/users/goekhanm/repos","events_url":"https://api.github.com/users/goekhanm/events{/privacy}","received_events_url":"https://api.github.com/users/goekhanm/received_events","type":"User","site_admin":false},"html_url":"https://github.com/goekhanm/wordpress","description":null,"fork":true,"url":"https://api.github.com/repos/goekhanm/wordpress","forks_url":"https://api.github.com/repos/goekhanm/wordpress/forks","keys_url":"https://api.github.com/repos/goekhanm/wordpress/keys{/key_id}","collaborators_url":"https://api.github.com/repos/goekhanm/wordpress/collaborators{/collaborator}","teams_url":"https://api.github.com/repos/goekhanm/wordpress/teams","hooks_url":"https://api.github.com/repos/goekhanm/wordpress/hooks","issue_events_url":"https://api.github.com/repos/goekhanm/wordpress/issues/events{/number}","events_url":"https://api.github.com/repos/goekhanm/wordpress/events","assignees_url":"https://api.github.com/repos/goekhanm/wordpress/assignees{/user}","branches_url":"https://api.github.com/repos/goekhanm/wordpress/branches{/branch}","tags_url":"https://api.github.com/repos/goekhanm/wordpress/tags","blobs_url":"https://api.github.com/repos/goekhanm/wordpress/git/blobs{/sha}","git_tags_url":"https://api.github.com/repos/goekhanm/wordpress/git/tags{/sha}","git_refs_url":"https://api.github.com/repos/goekhanm/wordpress/git/refs{/sha}","trees_url":"https://api.github.com/repos/goekhanm/wordpress/git/trees{/sha}","statuses_url":"https://api.github.com/repos/goekhanm/wordpress/statuses/{sha}","languages_url":"https://api.github.com/repos/goekhanm/wordpress/languages","stargazers_url":"https://api.github.com/repos/goekhanm/wordpress/stargazers","contributors_url":"https://api.github.com/repos/goekhanm/wordpress/contributors","subscribers_url":"https://api.github.com/repos/goekhanm/wordpress/subscribers","subscription_url":"https://api.github.com/repos/goekhanm/wordpress/subscription","commits_url":"https://api.github.com/repos/goekhanm/wordpress/commits{/sha}","git_commits_url":"https://api.github.com/repos/goekhanm/wordpress/git/commits{/sha}","comments_url":"https://api.github.com/repos/goekhanm/wordpress/comments{/number}","issue_comment_url":"https://api.github.com/repos/goekhanm/wordpress/issues/comments{/number}","contents_url":"https://api.github.com/repos/goekhanm/wordpress/contents/{+path}","compare_url":"https://api.github.com/repos/goekhanm/wordpress/compare/{base}...{head}","merges_url":"https://api.github.com/repos/goekhanm/wordpress/merges","archive_url":"https://api.github.com/repos/goekhanm/wordpress/{archive_format}{/ref}","downloads_url":"https://api.github.com/repos/goekhanm/wordpress/downloads","issues_url":"https://api.github.com/repos/goekhanm/wordpress/issues{/number}","pulls_url":"https://api.github.com/repos/goekhanm/wordpress/pulls{/number}","milestones_url":"https://api.github.com/repos/goekhanm/wordpress/milestones{/number}","notifications_url":"https://api.github.com/repos/goekhanm/wordpress/notifications{?since,all,participating}","labels_url":"https://api.github.com/repos/goekhanm/wordpress/labels{/name}","releases_url":"https://api.github.com/repos/goekhanm/wordpress/releases{/id}","deployments_url":"https://api.github.com/repos/goekhanm/wordpress/deployments","created_at":"2017-11-07T15:44:00Z","updated_at":"2017-11-07T15:44:06Z","pushed_at":"2017-02-22T17:02:44Z","git_url":"git://github.com/goekhanm/wordpress.git","ssh_url":"git@github.com:goekhanm/wordpress.git","clone_url":"https://github.com/goekhanm/wordpress.git","svn_url":"https://github.com/goekhanm/wordpress","homepage":null,"size":8039,"stargazers_count":0,"watchers_count":0,"language":"PHP","has_issues":false,"has_projects":true,"has_downloads":true,"has_wiki":true,"has_pages":false,"has_discussions":false,"forks_count":0,"mirror_url":null,"archived":false,"disabled":false,"open_issues_count":0,"license":{"key":"other","name":"Other","spdx_id":"NOASSERTION","url":null,"node_id":"MDc6TGljZW5zZTA="},"allow_forking":true,"is_template":false,"web_commit_signoff_required":false,"topics":[],"visibility":"public","forks":0,"open_issues":0,"watchers":0,"default_branch":"master","permissions":{"admin":false,"maintain":false,"push":false,"triage":false,"pull":true}}]