[{"login":"viljark","id":1067120,"node_id":"MDQ6VXNlcjEwNjcxMjA=","avatar_url":"https://avatars.githubusercontent.com/u/1067120?v=4","gravatar_id":"","url":"https://api.github.com/users/viljark","html_url":"https://github.com/viljark","followers_url":"https://api.github.com/users/viljark/followers","following_url":"https://api.github.com/users/viljark/following{/other_user}","gists_url":"https://api.github.com/users/viljark/gists{/gist_id}","starred_url":"https://api.github.com/users/viljark/starred{/owner}{/repo}","subscriptions_url":"https://api.github.com/users/viljark/subscriptions","organizations_url":"https://api.github.com/users/viljark/orgs","repos_url":"https://api.github.com/users/viljark/repos","events_url":"https://api.github.com/users/viljark/events{/privacy}","received_events_url":"https://api.github.com/users/viljark/received_events","type":"User","site_admin":false,"contributions":109},{"login":"henritrees","id":16324008,"node_id":"MDQ6VXNlcjE2MzI0MDA4","avatar_url":"https://avatars.githubusercontent.com/u/16324008?v=4","gravatar_id":"","url":"https://api.github.com/users/henritrees","html_url":"https://github.com/henritrees","followers_url":"https://api.github.com/users/henritrees/followers","following_url":"https://api.github.com/users/henritrees/following{/other_user}","gists_url":"https://api.github.com/users/henritrees/gists{/gist_id}","starred_url":"https://api.github.com/users/henritrees/starred{/owner}{/repo}","subscriptions_url":"https://api.github.com/users/henritrees/subscriptions","organizations_url":"https://api.github.com/users/henritrees/orgs","repos_url":"https://api.github.com/users/henritrees/repos","events_url":"https://api.github.com/users/henritrees/events{/privacy}","received_events_url":"https://api.github.com/users/henritrees/received_events","type":"User","site_admin":false,"contributions":65},{"login":"der-basti","id":9511040,"node_id":"MDQ6VXNlcjk1MTEwNDA=","avatar_url":"https://avatars.githubusercontent.com/u/9511040?v=4","gravatar_id":"","url":"https://api.github.com/users/der-basti","html_url":"https://github.com/der-basti","followers_url":"https://api.github.com/users/der-basti/followers","following_url":"https://api.github.com/users/der-basti/following{/other_user}","gists_url":"https://api.github.com/users/der-basti/gists{/gist_id}","starred_url":"https://api.github.com/users/der-basti/starred{/owner}{/repo}","subscriptions_url":"https://api.github.com/users/der-basti/subscriptions","organizations_url":"https://api.github.com/users/der-basti/orgs","repos_url":"https://api.github.com/users/der-basti/repos","events_url":"https://api.github.com/users/der-basti/events{/privacy}","received_events_url":"https://api.github.com/users/der-basti/received_events","type":"User","site_admin":false,"contributions":4},{"login":"littleladylizah","id":1439743,"node_id":"MDQ6VXNlcjE0Mzk3NDM=","avatar_url":"https://avatars.githubusercontent.com/u/1439743?v=4","gravatar_id":"","url":"https://api.github.com/users/littleladylizah","html_url":"https://github.com/littleladylizah","followers_url":"https://api.github.com/users/littleladylizah/followers","following_url":"https://api.github.com/users/littleladylizah/following{/other_user}","gists_url":"https://api.github.com/users/littleladylizah/gists{/gist_id}","starred_url":"https://api.github.com/users/littleladylizah/starred{/owner}{/repo}","subscriptions_url":"https://api.github.com/users/littleladylizah/subscriptions","organizations_url":"https://api.github.com/users/littleladylizah/orgs","repos_url":"https://api.github.com/users/littleladylizah/repos","events_url":"https://api.github.com/users/littleladylizah/events{/privacy}","received_events_url":"https://api.github.com/users/littleladylizah/received_events","type":"User","site_admin":false,"contributions":3}]