{"login":"romansey","id":1835713,"node_id":"MDQ6VXNlcjE4MzU3MTM=","avatar_url":"https://avatars.githubusercontent.com/u/1835713?v=4","gravatar_id":"","url":"https://api.github.com/users/romansey","html_url":"https://github.com/romansey","followers_url":"https://api.github.com/users/romansey/followers","following_url":"https://api.github.com/users/romansey/following{/other_user}","gists_url":"https://api.github.com/users/romansey/gists{/gist_id}","starred_url":"https://api.github.com/users/romansey/starred{/owner}{/repo}","subscriptions_url":"https://api.github.com/users/romansey/subscriptions","organizations_url":"https://api.github.com/users/romansey/orgs","repos_url":"https://api.github.com/users/romansey/repos","events_url":"https://api.github.com/users/romansey/events{/privacy}","received_events_url":"https://api.github.com/users/romansey/received_events","type":"User","site_admin":false,"name":"Roman Seyffarth","company":null,"blog":"","location":null,"email":null,"hireable":null,"bio":null,"twitter_username":null,"public_repos":9,"public_gists":0,"followers":6,"following":4,"created_at":"2012-06-10T14:42:17Z","updated_at":"2023-09-22T12:08:31Z"}