[{"login":"maiksensi","id":6359386,"node_id":"MDQ6VXNlcjYzNTkzODY=","avatar_url":"https://avatars.githubusercontent.com/u/6359386?v=4","gravatar_id":"","url":"https://api.github.com/users/maiksensi","html_url":"https://github.com/maiksensi","followers_url":"https://api.github.com/users/maiksensi/followers","following_url":"https://api.github.com/users/maiksensi/following{/other_user}","gists_url":"https://api.github.com/users/maiksensi/gists{/gist_id}","starred_url":"https://api.github.com/users/maiksensi/starred{/owner}{/repo}","subscriptions_url":"https://api.github.com/users/maiksensi/subscriptions","organizations_url":"https://api.github.com/users/maiksensi/orgs","repos_url":"https://api.github.com/users/maiksensi/repos","events_url":"https://api.github.com/users/maiksensi/events{/privacy}","received_events_url":"https://api.github.com/users/maiksensi/received_events","type":"User","site_admin":false,"contributions":2}]